odoo10_addon_account_financial_report_qweb-10.0.3.1.3-py3.6-nspkg.pth
odoo/addons/account_financial_report_qweb/README.rst
odoo/addons/account_financial_report_qweb/__init__.py
odoo/addons/account_financial_report_qweb/__manifest__.py
odoo/addons/account_financial_report_qweb/menuitems.xml
odoo/addons/account_financial_report_qweb/reports.xml
odoo/addons/account_financial_report_qweb/i18n/account_financial_report_qweb.pot
odoo/addons/account_financial_report_qweb/i18n/es.po
odoo/addons/account_financial_report_qweb/i18n/es_EC.po
odoo/addons/account_financial_report_qweb/i18n/fi.po
odoo/addons/account_financial_report_qweb/i18n/fr.po
odoo/addons/account_financial_report_qweb/i18n/hr_HR.po
odoo/addons/account_financial_report_qweb/i18n/it.po
odoo/addons/account_financial_report_qweb/i18n/nl.po
odoo/addons/account_financial_report_qweb/i18n/nl_NL.po
odoo/addons/account_financial_report_qweb/i18n/pt.po
odoo/addons/account_financial_report_qweb/i18n/tr.po
odoo/addons/account_financial_report_qweb/models/__init__.py
odoo/addons/account_financial_report_qweb/models/account.py
odoo/addons/account_financial_report_qweb/models/account_group.py
odoo/addons/account_financial_report_qweb/models/account_move_line.py
odoo/addons/account_financial_report_qweb/readme/CONTRIBUTORS.rst
odoo/addons/account_financial_report_qweb/readme/DESCRIPTION.rst
odoo/addons/account_financial_report_qweb/readme/HISTORY.rst
odoo/addons/account_financial_report_qweb/report/__init__.py
odoo/addons/account_financial_report_qweb/report/abstract_report.py
odoo/addons/account_financial_report_qweb/report/abstract_report_xlsx.py
odoo/addons/account_financial_report_qweb/report/aged_partner_balance.py
odoo/addons/account_financial_report_qweb/report/aged_partner_balance_xlsx.py
odoo/addons/account_financial_report_qweb/report/general_ledger.py
odoo/addons/account_financial_report_qweb/report/general_ledger_xlsx.py
odoo/addons/account_financial_report_qweb/report/journal_report.py
odoo10_addon_account_financial_report_qweb-10.0.3.1.3.dist-info/METADATA
odoo10_addon_account_financial_report_qweb-10.0.3.1.3.dist-info/WHEEL
odoo10_addon_account_financial_report_qweb-10.0.3.1.3.dist-info/namespace_packages.txt
odoo10_addon_account_financial_report_qweb-10.0.3.1.3.dist-info/top_level.txt
odoo10_addon_account_financial_report_qweb-10.0.3.1.3.dist-info/RECORD
