Metadata-Version: 2.1
Name: odoo10-addon-account-financial-report-qweb
Version: 10.0.3.1.3
Summary: OCA Financial Reports
Home-page: https://odoo-community.org/
Author: Camptocamp SA,initOS GmbH,redCOR AG,ACSONE SA/NV,Odoo Community Association (OCA)
Author-email: support@odoo-community.org
License: AGPL-3
Platform: UNKNOWN
Classifier: Programming Language :: Python
Classifier: Framework :: Odoo
Classifier: License :: OSI Approved :: GNU Affero General Public License v3
Requires-Python: ~=2.7
Requires-Dist: odoo10-addon-account-group
Requires-Dist: odoo10-addon-date-range
Requires-Dist: odoo10-addon-report-xlsx
Requires-Dist: odoo10-addon-web-widget-many2many-tags-multi-selection
Requires-Dist: odoo (<10.1dev,>=10.0)
